ashishdotme_utils_lib/__init__.py
ashishdotme_utils_lib/core/core.py
ashishdotme_utils_lib/errors/common_errors.py
ashishdotme_utils_lib/sdk/dashboard_client.py
ashishdotme_utils_lib/sdk/s3_client.py
ashishdotme_utils_lib-0.0.8.dist-info/METADATA
ashishdotme_utils_lib-0.0.8.dist-info/WHEEL
ashishdotme_utils_lib-0.0.8.dist-info/top_level.txt
ashishdotme_utils_lib-0.0.8.dist-info/RECORD
